CHANGES
MANIFEST.in
Makefile
README.md
requirements.txt
setup.py
kuankr/__init__.py
kuankr.egg-info/PKG-INFO
kuankr.egg-info/SOURCES.txt
kuankr.egg-info/dependency_links.txt
kuankr.egg-info/top_level.txt