Metadata-Version: 1.0
Name: kuankr
Version: 0.0.1
Summary: kuankr
Home-page: http://git.agutong.com/dev/kuankr
Author: dev
Author-email: dev@agutong.com
License: LICENSE
Platform: UNKNOWN
